carconnectivity_database/__init__.py
carconnectivity_database/carconnectivity_database_base.py
carconnectivity_plugin_database-0.4.2.dist-info/licenses/LICENSE
carconnectivity_plugins/database/__init__.py
carconnectivity_plugins/database/_version.py
carconnectivity_plugins/database/plugin.py
carconnectivity_plugins/database/agents/base_agent.py
carconnectivity_plugins/database/agents/charging_agent.py
carconnectivity_plugins/database/agents/climatization_agent.py
carconnectivity_plugins/database/agents/drive_state_agent.py
carconnectivity_plugins/database/agents/refuel_agent.py
carconnectivity_plugins/database/agents/state_agent.py
carconnectivity_plugins/database/agents/trip_agent.py
carconnectivity_plugins/database/model/__init__.py
carconnectivity_plugins/database/model/alembic.ini
carconnectivity_plugins/database/model/base.py
carconnectivity_plugins/database/model/battery_temperature.py
carconnectivity_plugins/database/model/charging_power.py
carconnectivity_plugins/database/model/charging_rate.py
carconnectivity_plugins/database/model/charging_session.py
carconnectivity_plugins/database/model/charging_state.py
carconnectivity_plugins/database/model/charging_station.py
carconnectivity_plugins/database/model/climatization_state.py
carconnectivity_plugins/database/model/connection_state.py
carconnectivity_plugins/database/model/datetime_decorator.py
carconnectivity_plugins/database/model/drive.py
carconnectivity_plugins/database/model/drive_consumption.py
carconnectivity_plugins/database/model/drive_level.py
carconnectivity_plugins/database/model/drive_range.py
carconnectivity_plugins/database/model/drive_range_full.py
carconnectivity_plugins/database/model/location.py
carconnectivity_plugins/database/model/migrations.py
carconnectivity_plugins/database/model/outside_temperature.py
carconnectivity_plugins/database/model/refuel_session.py
carconnectivity_plugins/database/model/state.py
carconnectivity_plugins/database/model/tag.py
carconnectivity_plugins/database/model/timedelta_decorator.py
carconnectivity_plugin_database-0.4.2.dist-info/METADATA
carconnectivity_plugin_database-0.4.2.dist-info/WHEEL
carconnectivity_plugin_database-0.4.2.dist-info/entry_points.txt
carconnectivity_plugin_database-0.4.2.dist-info/top_level.txt
carconnectivity_plugin_database-0.4.2.dist-info/RECORD
