Metadata-Version: 2.4
Name: carconnectivity-plugin-database
Version: 0.4.2
Summary: CarConnectivity plugin for storing data to Databases
Author: Till Steinbach
License-Expression: MIT
Classifier: Development Status :: 3 - Alpha
Classifier: Intended Audience :: End Users/Desktop
Classifier: Intended Audience :: System Administrators
Classifier: Programming Language :: Python :: 3.9
Classifier: Programming Language :: Python :: 3.10
Classifier: Programming Language :: Python :: 3.11
Classifier: Programming Language :: Python :: 3.12
Classifier: Programming Language :: Python :: 3.13
Classifier: Programming Language :: Python :: 3.14
Classifier: Topic :: Utilities
Classifier: Topic :: System :: Monitoring
Classifier: Topic :: Home Automation
Requires-Python: >=3.9
License-File: LICENSE
Requires-Dist: carconnectivity>=0.11.5
Requires-Dist: sqlalchemy~=2.0.45
Requires-Dist: psycopg2-binary~=2.9.11
Requires-Dist: alembic~=1.17.2
Requires-Dist: SQLAlchemy-Utc~=0.14.0
Requires-Dist: flask_sqlalchemy~=3.1.1
Dynamic: license-file
